haulsrv/__init__.py
haulsrv/__main__.py
haulsrv/settings.py
haulsrv/cli/__init__.py
haulsrv/cli/init.py
haulsrv/cli/main.py
haulsrv/cli/settings.py
haulsrv/cli/start.py
haulsrv/core/__init__.py
haulsrv/core/server.py
haulsrv/core/topics.py
haulsrv/core/worker_class.py
haulsrv/core/api/__init__.py
haulsrv/core/api/api_server.py
haulsrv/core/api/app.py
haulsrv/core/api/test_app/test_cluster.py
haulsrv/core/api/test_app/test_consume.py
haulsrv/core/api/test_app/test_probes.py
haulsrv/core/api/test_app/test_produce.py
haulsrv/core/api/test_app/test_root.py
haulsrv/core/api/test_app/test_topics.py
haulsrv/core/ui/__init__.py
haulsrv/core/ui/app.py
haulsrv/core/ui/ui_server.py
haulsrv-0.0.0.dist-info/LICENSE
haulsrv-0.0.0.dist-info/METADATA
haulsrv-0.0.0.dist-info/WHEEL
haulsrv-0.0.0.dist-info/top_level.txt
haulsrv-0.0.0.dist-info/RECORD
